[
  {
    "_id": "5b33edb851e95f0ddbfbc2b8",
    "picture": "http://placehold.it/32x32",
    "user": "Lottie",
    "tags": ["duis", "in", "deserunt", "amet", "fugiat", "in", "adipisicing"]
  },
  {
    "_id": "5b33edb8c21eac295224e80c",
    "picture": "http://placehold.it/32x32",
    "user": "Sharp",
    "tags": ["qui", "non", "tempor", "velit", "dolor", "amet", "aliquip"]
  },
  {
    "_id": "5b33edb857385ddfc2368264",
    "picture": "http://placehold.it/32x32",
    "user": "Adrian",
    "tags": ["do", "irure", "nisi", "est", "adipisicing", "est", "excepteur"]
  },
  {
    "_id": "5b33edb84256cf0c5c47fe12",
    "picture": "http://placehold.it/32x32",
    "user": "Moran",
    "tags": [
      "mollit",
      "tempor",
      "enim",
      "proident",
      "fugiat",
      "adipisicing",
      "in"
    ]
  },
  {
    "_id": "5b33edb8104f4d6720139eff",
    "picture": "http://placehold.it/32x32",
    "user": "May",
    "tags": ["do", "proident", "esse", "ea", "commodo", "exercitation", "est"]
  },
  {
    "_id": "5b33edb8acc8027a00c9feec",
    "picture": "http://placehold.it/32x32",
    "user": "Ashlee",
    "tags": [
      "dolor",
      "eiusmod",
      "reprehenderit",
      "laborum",
      "anim",
      "tempor",
      "voluptate"
    ]
  },
  {
    "_id": "5b33edb884969f5c5451a32c",
    "picture": "http://placehold.it/32x32",
    "user": "Patrica",
    "tags": ["sit", "esse", "in", "deserunt", "in", "cupidatat", "ea"]
  },
  {
    "_id": "5b33edb867e076b68488a125",
    "picture": "http://placehold.it/32x32",
    "user": "Cherry",
    "tags": [
      "aliqua",
      "cupidatat",
      "sint",
      "dolore",
      "reprehenderit",
      "aute",
      "id"
    ]
  },
  {
    "_id": "5b33edb809e4046c83e09ac4",
    "picture": "http://placehold.it/32x32",
    "user": "Imogene",
    "tags": [
      "ut",
      "fugiat",
      "officia",
      "incididunt",
      "mollit",
      "enim",
      "aliqua"
    ]
  },
  {
    "_id": "5b33edb831b032b991f25616",
    "picture": "http://placehold.it/32x32",
    "user": "Doyle",
    "tags": [
      "velit",
      "consequat",
      "officia",
      "irure",
      "irure",
      "est",
      "laborum"
    ]
  },
  {
    "_id": "5b33edb84e1bb42e45eb6685",
    "picture": "http://placehold.it/32x32",
    "user": "Candy",
    "tags": [
      "magna",
      "exercitation",
      "commodo",
      "mollit",
      "exercitation",
      "est",
      "id"
    ]
  },
  {
    "_id": "5b33edb8acdfb637459746e8",
    "picture": "http://placehold.it/32x32",
    "user": "Oliver",
    "tags": ["et", "dolor", "deserunt", "labore", "enim", "sint", "duis"]
  },
  {
    "_id": "5b33edb8d98383d4e20686c0",
    "picture": "http://placehold.it/32x32",
    "user": "Eula",
    "tags": [
      "dolore",
      "eu",
      "excepteur",
      "laborum",
      "excepteur",
      "consectetur",
      "duis"
    ]
  },
  {
    "_id": "5b33edb8245ea9ff99076f6f",
    "picture": "http://placehold.it/32x32",
    "user": "Josie",
    "tags": ["eu", "pariatur", "nisi", "culpa", "tempor", "aute", "minim"]
  },
  {
    "_id": "5b33edb86f76d56da4023a6e",
    "picture": "http://placehold.it/32x32",
    "user": "Bernice",
    "tags": [
      "ullamco",
      "ullamco",
      "duis",
      "sit",
      "consectetur",
      "exercitation",
      "ut"
    ]
  },
  {
    "_id": "5b33edb84d6e13c600f6b8d3",
    "picture": "http://placehold.it/32x32",
    "user": "Munoz",
    "tags": ["aute", "veniam", "laborum", "magna", "sunt", "velit", "in"]
  },
  {
    "_id": "5b33edb88cdef9cbc5d24375",
    "picture": "http://placehold.it/32x32",
    "user": "Madeleine",
    "tags": ["aliqua", "non", "irure", "dolore", "aute", "laboris", "fugiat"]
  },
  {
    "_id": "5b33edb8c5ec93582583e67b",
    "picture": "http://placehold.it/32x32",
    "user": "Lessie",
    "tags": [
      "non",
      "labore",
      "aliqua",
      "adipisicing",
      "tempor",
      "minim",
      "pariatur"
    ]
  },
  {
    "_id": "5b33edb84912dd2d6eb1c990",
    "picture": "http://placehold.it/32x32",
    "user": "Holmes",
    "tags": ["deserunt", "dolore", "veniam", "nisi", "amet", "sit", "proident"]
  },
  {
    "_id": "5b33edb884dc883389bc1529",
    "picture": "http://placehold.it/32x32",
    "user": "Christy",
    "tags": [
      "et",
      "excepteur",
      "ipsum",
      "labore",
      "exercitation",
      "irure",
      "adipisicing"
    ]
  }
]
